{
  "operationId": "fetchAllProgramProjects",
  "summary": "Fetches A Page of projects for a program",
  "description": "Fetch Projects",
  "tags": [
    "Program"
  ],
  "parameters": [
    {
      "$ref": "../../../components/parameters/programId.json"
    },
    {
      "$ref": "../../../components/parameters/limit.json"
    },
    {
      "$ref": "../../../components/parameters/offset.json"
    },
    {
      "$ref": "../../../components/parameters/projectSort.json"
    },
    {
      "$ref": "../../../components/parameters/filterLabel.json"
    }
  ],
  "responses": {
    "200": {
      "$ref": "../../../components/responses/projectPage.json"
    },
    "401": {
      "$ref": "../../../components/responses/unauthorized.json"
    },
    "403": {
      "$ref": "../../../components/responses/forbidden.json"
    }
  }
}
