{
  "description": "Paged vendor response",
  "content": {
    "application/hal+json": {
      "schema": {
        "properties": {
          "_embedded": {
            "type": "object",
            "properties": {
              "nter:vendors": {
                "type": "array",
                "items": {
                  "type": "object",
                  "allOf": [
                    {
                      "$ref": "../schemas/vendor.json"
                    },
                    {
                      "$ref": "../schemas/links/self.json"
                    }
                  ]
                }
              }
            }
          }
        },
        "allOf": [
          {
            "$ref": "../schemas/links/nextOffset.json"
          },
          {
            "$ref": "../schemas/links/self.json"
          }
        ]
      }
    }
  }
}
