{
  "operationId": "fetchAllCustomerProjects",
  "summary": "Fetches A Page of projects for the customer",
  "description": "Fetch customer projects",
  "tags": [
    "Customer"
  ],
  "parameters": [
    {
      "$ref": "../../../components/parameters/customerId.json"
    },
    {
      "$ref": "../../../components/parameters/limit.json"
    },
    {
      "$ref": "../../../components/parameters/offset.json"
    },
    {
      "$ref": "../../../components/parameters/projectSort.json"
    },
    {
      "$ref": "../../../components/parameters/filterLabel.json"
    },
    {
      "$ref": "../../../components/parameters/filterProgram.json"
    }
  ],
  "responses": {
    "200": {
      "$ref": "../../../components/responses/projectPage.json"
    },
    "401": {
      "$ref": "../../../components/responses/401unauthorized.json"
    },
    "404": {
      "$ref": "../../../components/responses/404notFound.json"
    },
    "403": {
      "$ref": "../../../components/responses/403forbidden.json"
    }
  }
}
