{
  "get": {
    "operationId": "fetchAllFacilities",
    "summary": "Fetch facilities",
    "description": "Fetches A Page of facilities",
    "tags": [
      "Location"
    ],
    "parameters": [
      {
        "$ref": "../../components/parameters/limit.json"
      },
      {
        "$ref": "../../components/parameters/offset.json"
      }
    ],
    "responses": {
      "200": {
        "$ref": "../../components/responses/halLocationPage.json"
      }
    },
    "security": [
      {
        "niagara": [
          "location:all"
        ]
      }
    ]
  }
}
