{
  "description": "Step to close or fail",
  "content": {
    "application/json": {
      "schema": {
        "type": "object",
        "description": "Close step",
        "allOf": [
          {
            "$ref": "../../components/schemas/workflow/close/allCloseSteps.json"
          }
        ]
      }
    },
    "application/vnd.fail-step+json": {
      "schema": {
        "type": "object",
        "description": "Fail step",
        "allOf": [
          {
            "$ref": "../../components/schemas/workflow/close/allCloseSteps.json"
          }
        ]
      }
    }
  }
}
